planqtn/__init__.py
planqtn/legos.py
planqtn/legos_test.py
planqtn/linalg.py
planqtn/linalg_test.py
planqtn/parity_check.py
planqtn/parity_check_test.py
planqtn/pauli.py
planqtn/poly.py
planqtn/poly_test.py
planqtn/progress_reporter.py
planqtn/progress_reporter_test.py
planqtn/stabilizer_tensor_enumerator.py
planqtn/stabilizer_tensor_enumerator_test.py
planqtn/symplectic.py
planqtn/symplectic_test.py
planqtn/tensor_network.py
planqtn/tensor_network_test.py
planqtn/networks/__init__.py
planqtn/networks/compass_code.py
planqtn/networks/compass_code_test.py
planqtn/networks/css_tanner_code.py
planqtn/networks/css_tanner_code_test.py
planqtn/networks/rotated_surface_code.py
planqtn/networks/rotated_surface_code_test.py
planqtn/networks/stabilizer_measurement_state_prep.py
planqtn/networks/stabilizer_measurement_state_prep_test.py
planqtn/networks/stabilizer_tanner_code.py
planqtn/networks/stabilizer_tanner_code_test.py
planqtn/networks/surface_code.py
planqtn/networks/surface_code_test.py
planqtn-0.1.0.dist-info/METADATA
planqtn-0.1.0.dist-info/WHEEL
planqtn-0.1.0.dist-info/licenses/LICENSE
planqtn-0.1.0.dist-info/RECORD
