Metadata-Version: 2.4
Name: planqtn
Version: 0.1.0
Summary: PlanqTN is a tensor network quantum error correction library implementation of the quantum LEGO framework.
Project-URL: Homepage, https://github.com/planqtn/planqtn
Project-URL: Issues, https://github.com/planqtn/planqtn/issues
Author-email: Balint Pato <balint@planqtn.com>
Maintainer-email: PlanqTN Contributors <planqtn@planqtn.com>
License-Expression: Apache-2.0
License-File: LICENSE
Classifier: Operating System :: OS Independent
Classifier: Programming Language :: Python :: 3
Requires-Python: >=3.9
Requires-Dist: attrs
Requires-Dist: celery
Requires-Dist: cmaes
Requires-Dist: cotengra
Requires-Dist: galois
Requires-Dist: matplotlib
Requires-Dist: networkx
Requires-Dist: numpy
Requires-Dist: python-socketio>=5.10.0
Requires-Dist: pyzx
Requires-Dist: quimb
Requires-Dist: redis
Requires-Dist: scipy
Requires-Dist: supabase
Requires-Dist: sympy
Provides-Extra: dev
Requires-Dist: aiohttp; extra == 'dev'
Requires-Dist: black==25.1.0; extra == 'dev'
Requires-Dist: flake8; extra == 'dev'
Requires-Dist: ipython; extra == 'dev'
Requires-Dist: mypy==1.16.0; extra == 'dev'
Requires-Dist: pydantic-to-typescript==2.0.0; extra == 'dev'
Requires-Dist: pylint==3.3.7; extra == 'dev'
Requires-Dist: pytest; extra == 'dev'
Requires-Dist: pytest-cov; extra == 'dev'
Requires-Dist: scipy-stubs; extra == 'dev'
Requires-Dist: types-tqdm; extra == 'dev'
